{
  "run_info": {
    "dataset": "users2.json",
    "config": "balanced_original",
    "run": 5,
    "execution_time": 284.2470500469208,
    "iterations_completed": 14,
    "max_iterations": 200,
    "terminated_early": true,
    "generations_without_improvement": 12,
    "pareto_size": 7,
    "pareto_points": [
      [
        610272.2499999999,
        2023.7900000000002
      ],
      [
        605438.72,
        2001.8000000000004
      ],
      [
        610394.010000001,
        2040.9000000000003
      ],
      [
        602736.6200000002,
        1967.9300000000003
      ],
      [
        619398.3000000006,
        2103.2000000000003
      ],
      [
        604599.6600000005,
        1981.1500000000003
      ],
      [
        611676.0399999993,
        2088.1500000000005
      ]
    ],
    "solutions_evaluated": 280,
    "config_params": {
      "n_ants": 20,
      "rho": 0.4,
      "alpha": 1.0,
      "beta": 3.0,
      "archive_size": 100,
      "no_improvement_generations": 12
    }
  },
  "solutions_count": 7,
  "solutions_directory": "../results/PACO\\solutions\\users2\\balanced_original\\run5",
  "objective_statistics": {
    "cost_range": {
      "min": 1967.9300000000003,
      "max": 2103.2000000000003
    },
    "minutes_range": {
      "min": 602736.6200000002,
      "max": 619398.3000000006
    }
  },
  "algorithm_info": {
    "archive_history_length": 14,
    "max_archive_size_reached": 7
  }
}